[
	{"input":"2H","name":"2H","damage":"1000, 300","guard":"All","startup":"11","active":"3, 3","recovery":"24","hit":"&#039;&#039;&#039;-6&#039;&#039;&#039;&lt;/span&gt;","block":"&#039;&#039;&#039;-10&#039;&#039;&#039;&lt;/span&gt;","invincibility":"-"},
	{"input":"2L","name":"2L","damage":"400","guard":"Low","startup":"6","active":"3","recovery":"10","hit":"&lt;span style=&quot;color: \n#00d7c0&quot; &gt;&#039;&#039;&#039;+2&#039;&#039;&#039;&lt;/span&gt;","block":"&#039;&#039;&#039;-2&#039;&#039;&#039;&lt;/span&gt;","invincibility":"-"},
	{"input":"2M","name":"2M","damage":"900","guard":"Mid","startup":"7","active":"3","recovery":"15","hit":"&lt;span style=&quot;color: \n#00d7c0&quot; &gt;&#039;&#039;&#039;+1&#039;&#039;&#039;&lt;/span&gt;","block":"&#039;&#039;&#039;-3&#039;&#039;&#039;&lt;/span&gt;","invincibility":"-"},
	{"input":"2U","name":"2U","damage":"1000","guard":"Low","startup":"7","active":"3","recovery":"24","hit":"HKD +43","block":"&#039;&#039;&#039;-12&#039;&#039;&#039;&lt;/span&gt;","invincibility":"-"},
	{"input":"66H","name":"66H","damage":"1200","guard":"Mid","startup":"15","active":"4","recovery":"23","hit":"&#039;&#039;&#039;+10&#039;&#039;&#039;&lt;/span&gt;","block":"&#039;&#039;&#039;-8 &#039;&#039;&#039;&lt;/span&gt;","invincibility":"-"},
	{"input":"66L","name":"66L","damage":"1000","guard":"Mid","startup":"8","active":"3","recovery":"10 [15]","hit":"&#039;&#039;&#039;+6&#039;&#039;&#039;&lt;/span&gt;","block":"&lt;span style=&quot;color: \n#00d7c0&quot; &gt;&#039;&#039;&#039;+2 &#039;&#039;&#039;&lt;/span&gt;","invincibility":"-"},
	{"input":"66M","name":"66M","damage":"1100","guard":"Low","startup":"12","active":"4","recovery":"21","hit":"KD","block":"&#039;&#039;&#039;-8 &#039;&#039;&#039;&lt;/span&gt;","invincibility":"-"},
	{"input":"近H","name":"近H","damage":"1000, 200×2","guard":"All","startup":"8","active":"2, 2, 2","recovery":"21","hit":"0","block":"&#039;&#039;&#039;-4&#039;&#039;&#039;&lt;/span&gt;","invincibility":"-"},
	{"input":"近L","name":"近L","damage":"600","guard":"All","startup":"5","active":"3","recovery":"6","hit":"&#039;&#039;&#039;+8&#039;&#039;&#039;&lt;/span&gt;","block":"&lt;span style=&quot;color: \n#00d7c0&quot; &gt;&#039;&#039;&#039;+4&#039;&#039;&#039;&lt;/span&gt;","invincibility":"-"},
	{"input":"近M","name":"近M","damage":"1100","guard":"All","startup":"6","active":"3","recovery":"14","hit":"&lt;span style=&quot;color: \n#00d7c0&quot; &gt;&#039;&#039;&#039;+2&#039;&#039;&#039;&lt;/span&gt;","block":"&#039;&#039;&#039;-2&#039;&#039;&#039;&lt;/span&gt;","invincibility":"-"},
	{"input":"近XX","name":"近XX","damage":"700","guard":"All","startup":"9","active":"3","recovery":"15","hit":"&lt;span style=&quot;color: \n#00d7c0&quot; &gt;&#039;&#039;&#039;+1&#039;&#039;&#039;&lt;/span&gt;","block":"&#039;&#039;&#039;-3&#039;&#039;&#039;&lt;/span&gt;","invincibility":"-"},
	{"input":"近XX6H","name":"近XX6H","damage":"700","guard":"High","startup":"18","active":"3","recovery":"21","hit":"&lt;span style=&quot;color: \n#00d7c0&quot; &gt;&#039;&#039;&#039;+1&#039;&#039;&#039;&lt;/span&gt;","block":"&#039;&#039;&#039;-4 &#039;&#039;&#039;&lt;/span&gt;","invincibility":"-"},
	{"input":"近XX6M","name":"近XX6M","damage":"700","guard":"Low","startup":"12","active":"3","recovery":"16","hit":"KD +51","block":"-4","invincibility":"-"},
	{"input":"近XXX","name":"近XXX","damage":"700","guard":"All","startup":"12","active":"3","recovery":"18","hit":"0","block":"&#039;&#039;&#039;-4&#039;&#039;&#039;&lt;/span&gt;","invincibility":"-"},
	{"input":"遠H","name":"遠H","damage":"1300","guard":"All","startup":"10","active":"6","recovery":"19","hit":"&#039;&#039;&#039;-4&#039;&#039;&#039;&lt;/span&gt;","block":"&#039;&#039;&#039;-8&#039;&#039;&#039;&lt;/span&gt;","invincibility":"-"},
	{"input":"遠L","name":"遠L","damage":"600","guard":"Low","startup":"6","active":"3","recovery":"8","hit":"&#039;&#039;&#039;+6&#039;&#039;&#039;&lt;/span&gt;","block":"&lt;span style=&quot;color: \n#00d7c0&quot; &gt;&#039;&#039;&#039;+2&#039;&#039;&#039;&lt;/span&gt;","invincibility":"-"},
	{"input":"遠M","name":"遠M","damage":"600, 300","guard":"All","startup":"9","active":"3, 1","recovery":"21","hit":"&#039;&#039;&#039;-3&#039;&#039;&#039;&lt;/span&gt;","block":"&#039;&#039;&#039;-7&#039;&#039;&#039;&lt;/span&gt;","invincibility":"-"},
	{"input":"jH","name":"jH","damage":"500×2","guard":"High/Air, All","startup":"8","active":"4(3)3","recovery":"Until L+1","hit":"-","block":"-","invincibility":"-"},
	{"input":"jL","name":"jL","damage":"600","guard":"High/Air","startup":"5","active":"Until L","recovery":"Until L+1","hit":"-","block":"-","invincibility":"-"},
	{"input":"jM","name":"jM","damage":"400×2","guard":"High/Air, All","startup":"6","active":"3,3","recovery":"Until L+1","hit":"-","block":"-","invincibility":"-"},
	{"input":"jU","name":"jU","damage":"250×n","guard":"All","startup":"19","active":"3×n","recovery":"11","hit":"&lt;span style=&quot;color: \n#00d7c0&quot; &gt;&#039;&#039;&#039;+2&#039;&#039;&#039;&lt;/span&gt;","block":"&#039;&#039;&#039;-2&#039;&#039;&#039;&lt;/span&gt;","invincibility":"-"},
	{"input":"ブレイブカウンター","name":"ブレイブカウンター","damage":"500","guard":"Mid","startup":"10","active":"-","recovery":"Total 31","hit":"Air Recovery &#039;&#039;&#039;+21&#039;&#039;&#039;&lt;/span&gt;","block":"&lt;span style=&quot;color: \n#00d7c0&quot; &gt;&#039;&#039;&#039;+6&#039;&#039;&#039;&lt;/span&gt;","invincibility":"-"},
	{"input":"空投げ(jLU)","name":"jLU","damage":"2500","guard":"Throw","startup":"5","active":"5","recovery":"Until L+ 6","hit":"HKD +44","block":"N/A","invincibility":"-"},
	{"input":"投げ(LU)","name":"LU","damage":"2500","guard":"Throw","startup":"4","active":"3","recovery":"31","hit":"HKD +44","block":"N/A","invincibility":"-"},
	{"input":"レイジングストライク(MH)","name":"MH","damage":"1500","guard":"Guard Crush 45 [52]","startup":"28","active":"1","recovery":"37","hit":"&#039;&#039;&#039;+15&#039;&#039;&#039;&lt;/span&gt;","block":"&#039;&#039;&#039;+8&#039;&#039;&#039;&lt;/span&gt; &#039;&#039;&#039;[+15]&#039;&#039;&#039;&lt;/span&gt;","invincibility":"-"},
	{"input":"レイジングチェイン(MHMH)","name":"MHMH","damage":"1000","guard":"Mid","startup":"13","active":"-","recovery":"-","hit":"+15","block":"-","invincibility":"-"},
	{"input":"H華嵐(214H)","name":"214H","damage":"900×2","guard":"All","startup":"42","active":"3,3","recovery":"12","hit":"&#039;&#039;&#039;+6&#039;&#039;&#039;&lt;/span&gt;","block":"&lt;span style=&quot;color: \n#00d7c0&quot; &gt;&#039;&#039;&#039;+2&#039;&#039;&#039;&lt;/span&gt;","invincibility":"1-14 Full"},
	{"input":"HM華嵐(214H-M)","name":"214H-M","damage":"1500","guard":"Low","startup":"38","active":"6","recovery":"15","hit":"KD","block":"&#039;&#039;&#039;-4&#039;&#039;&#039;&lt;/span&gt;","invincibility":"1-14 Full"},
	{"input":"L華嵐(214L)","name":"214L","damage":"600×2","guard":"All","startup":"46","active":"3,3","recovery":"13","hit":"&lt;span style=&quot;color: \n#00d7c0&quot; &gt;&#039;&#039;&#039;+5&#039;&#039;&#039;&lt;/span&gt;","block":"&lt;span style=&quot;color: \n#00d7c0&quot; &gt;&#039;&#039;&#039;+1&#039;&#039;&#039;&lt;/span&gt;","invincibility":"3-15 Full"},
	{"input":"M華嵐(214M)","name":"214M","damage":"1000","guard":"Low","startup":"41","active":"6","recovery":"18","hit":"KD","block":"&#039;&#039;&#039;-7&#039;&#039;&#039;&lt;/span&gt;","invincibility":"3-15 Full"},
	{"input":"U華嵐(214U)","name":"214U","damage":"500×3, 800","guard":"Mid","startup":"22","active":"3,3,3,1","recovery":"10","hit":"HKD +63","block":"&lt;span style=&quot;color: \n#00d7c0&quot; &gt;&#039;&#039;&#039;+4&#039;&#039;&#039;&lt;/span&gt;","invincibility":"-"},
	{"input":"H狐火(22H)","name":"22H","damage":"1200","guard":"All","startup":"23","active":"9","recovery":"14","hit":"&#039;&#039;&#039;+8&#039;&#039;&#039;&lt;/span&gt;","block":"&lt;span style=&quot;color: \n#00d7c0&quot; &gt;&#039;&#039;&#039;+4&#039;&#039;&#039;&lt;/span&gt;","invincibility":"-"},
	{"input":"L狐火(22L)","name":"22L","damage":"800","guard":"All","startup":"21","active":"9","recovery":"17","hit":"&lt;span style=&quot;color: \n#00d7c0&quot; &gt;&#039;&#039;&#039;+4&#039;&#039;&#039;&lt;/span&gt;","block":";&#039;&#039;&#039;0&#039;&#039;&#039;&lt;/span&gt;","invincibility":"-"},
	{"input":"M狐火(22M)","name":"22M","damage":"1000","guard":"All","startup":"31","active":"9","recovery":"13","hit":"&#039;&#039;&#039;+9&#039;&#039;&#039;&lt;/span&gt;","block":"&#039;&#039;&#039;+5&#039;&#039;&#039;&lt;/span&gt;","invincibility":"-"},
	{"input":"U狐火(22U)","name":"22U","damage":"600×3","guard":"Mid","startup":"9","active":"1,1,3","recovery":"14","hit":"&#039;&#039;&#039;+10&#039;&#039;&#039;&lt;/span&gt;","block":"&#039;&#039;&#039;+6&#039;&#039;&#039;&lt;/span&gt;","invincibility":"-"},
	{"input":"H夜天光(236H)","name":"236H","damage":"100×6, 700","guard":"All","startup":"14","active":"2×6,7 [2x6]","recovery":"16 [12]","hit":"KD","block":"&#039;&#039;&#039;-6&#039;&#039;&#039;&lt;/span&gt;","invincibility":"-"},
	{"input":"L夜天光(236L)","name":"236L","damage":"300×3","guard":"All","startup":"14","active":"4×3 [4x2]","recovery":"16 [12]","hit":"KD","block":"&#039;&#039;&#039;-3&#039;&#039;&#039;&lt;/span&gt;","invincibility":"-"},
	{"input":"M夜天光(236M)","name":"236M","damage":"100×6, 500","guard":"All","startup":"18","active":"2×6,4 [2x6]","recovery":"21 [12]","hit":"KD +48","block":"&#039;&#039;&#039;-8&#039;&#039;&#039;&lt;/span&gt;","invincibility":"-"},
	{"input":"U夜天光(236U)","name":"236U","damage":"400, 200×8, 700","guard":"Mid","startup":"13","active":"2x8","recovery":"20","hit":"HKD +45","block":"&#039;&#039;&#039;-4&#039;&#039;&#039;&lt;/span&gt;","invincibility":"-"},
	{"input":"H飛燕・焔返し(623H)","name":"623H","damage":"100×10, 500","guard":"All","startup":"11","active":"2×10(11)2","recovery":"34","hit":"KD","block":"&#039;&#039;&#039;-36&#039;&#039;&#039;&lt;/span&gt;","invincibility":"1-28 Full"},
	{"input":"L飛燕・焔返し(623L)","name":"623L","damage":"200×5","guard":"All","startup":"6","active":"2×5","recovery":"27","hit":"KD +52","block":"&#039;&#039;&#039;-12&#039;&#039;&#039;&lt;/span&gt;","invincibility":"-"},
	{"input":"M飛燕・焔返し(623M)","name":"623M","damage":"200×4, 100×3","guard":"All","startup":"9","active":"2×8","recovery":"33","hit":"Air Recovery +16","block":"&#039;&#039;&#039;-26&#039;&#039;&#039;&lt;/span&gt;","invincibility":"1-14 Full"},
	{"input":"U飛燕・焔返し(623U)","name":"623U","damage":"100×10, 1000","guard":"Mid","startup":"8","active":"2x10(22)4","recovery":"26","hit":"HKD +39","block":"&#039;&#039;&#039;-52&#039;&#039;&#039;&lt;/span&gt;","invincibility":"1-34 Full"},
	{"input":"C紅之舞・凜炎改(236236H)","name":"236236H","damage":"1000, 100×6, 450×2, 1500","guard":"Mid","startup":"9+5","active":"-","recovery":"-","hit":"HKD +46","block":"&#039;&#039;&#039;-23&#039;&#039;&#039;&lt;/span&gt;","invincibility":"1-14 All, 15-16 Strike/Throw"},
	{"input":"S蒼紅之舞・竜胆(236236U)","name":"236236U","damage":"120×19, 1320, 2400 [100×19, 2100]","guard":"Mid","startup":"7+7","active":"3×20","recovery":"40","hit":"HKD +43 [HKD +46]","block":"&#039;&#039;&#039;-24&#039;&#039;&#039;&lt;/span&gt;","invincibility":"1~22 All"},
	{"input":"参之毎(5U)","name":"5U","damage":"-","guard":"-","startup":"-","active":"-","recovery":"20","hit":"-","block":"-","invincibility":"-"},
	{"input":"融月(k2H)","name":"k2H","damage":"1300","guard":"All","startup":"11","active":"6","recovery":"24","hit":"KD","block":"&#039;&#039;&#039;-13&#039;&#039;&#039;&lt;/span&gt;","invincibility":"-"},
	{"input":"構え2L(k2L)","name":"k2L","damage":"800","guard":"All","startup":"8","active":"3","recovery":"15","hit":"Air Recovery +23","block":"&#039;&#039;&#039;-3&#039;&#039;&#039;&lt;/span&gt;","invincibility":"-"},
	{"input":"構え2M(k2M)","name":"k2M","damage":"900","guard":"Low","startup":"10","active":"6","recovery":"5","hit":"&#039;&#039;&#039;+6&#039;&#039;&#039;&lt;/span&gt;","block":"&lt;span style=&quot;color: \n#00d7c0&quot; &gt;&#039;&#039;&#039;+2&#039;&#039;&#039;&lt;/span&gt;","invincibility":"7-18 Low Profile"},
	{"input":"構え後ろステップ(k44)","name":"k44","damage":"-","guard":"-","startup":"-","active":"-","recovery":"17","hit":"-","block":"-","invincibility":"8~11 Low"},
	{"input":"紅蓮(k5H)","name":"k5H","damage":"1600","guard":"All","startup":"15[29]","active":"11","recovery":"14","hit":"-","block":"&#039;&#039;&#039;-6&#039;&#039;&#039;&lt;/span&gt;","invincibility":"-"},
	{"input":"構え5L(k5L)","name":"k5L","damage":"600","guard":"All","startup":"5","active":"3","recovery":"8","hit":"&lt;span style=&quot;color: \n#00d7c0&quot; &gt;&#039;&#039;&#039;+4&#039;&#039;&#039;&lt;/span&gt;","block":";&#039;&#039;&#039;0&#039;&#039;&#039;&lt;/span&gt;","invincibility":"-"},
	{"input":"構え5M(k5M)","name":"k5M","damage":"1100","guard":"All","startup":"16","active":"4","recovery":"11","hit":"&#039;&#039;&#039;+7&#039;&#039;&#039;&lt;/span&gt;","block":"&lt;span style=&quot;color: \n#00d7c0&quot; &gt;&#039;&#039;&#039;+2&#039;&#039;&#039;&lt;/span&gt;","invincibility":"10-19 Low"},
	{"input":"構え前ステップ(k66)","name":"k66","damage":"-","guard":"-","startup":"-","active":"-","recovery":"14","hit":"-","block":"-","invincibility":"-"},
	{"input":"燕返し(k当て身)","name":"k当て身","damage":"1000","guard":"All","startup":"0","active":"10","recovery":"25","hit":"KD","block":"&#039;&#039;&#039;-13&#039;&#039;&#039;&lt;/span&gt;","invincibility":"1-Active Full"},
	{"input":"構え投げ(k投げ)","name":"k投げ","damage":"2500","guard":"Throw","startup":"20","active":"3","recovery":"25","hit":"HKD +44","block":"-","invincibility":"3~13 Airborne"},
	{"input":"構え解除(kU)","name":"kU","damage":"-","guard":"-","startup":"-","active":"-","recovery":"12","hit":"-","block":"-","invincibility":"-"}
]